Metadata-Version: 2.1
Name: gameslib
Version: 0.1.0
Summary: Everything you need to have for a basic Console-only Game in Python.
Home-page: 
Author: TRC Loop
Author-email: aro.yt.mail@gmail.com
License: MIT
Keywords: game,console,terminal
Platform: UNKNOWN
Classifier: License :: OSI Approved :: MIT License
Classifier: Programming Language :: Python :: 3
License-File: LICENSE.txt
